LICENSE
MANIFEST.in
README.rst
setup.py
src/sentry_redispubsub/__init__.py
src/sentry_redispubsub/forms.py
src/sentry_redispubsub/plugin.py
src/sentry_redispubsub.egg-info/PKG-INFO
src/sentry_redispubsub.egg-info/SOURCES.txt
src/sentry_redispubsub.egg-info/dependency_links.txt
src/sentry_redispubsub.egg-info/entry_points.txt
src/sentry_redispubsub.egg-info/not-zip-safe
src/sentry_redispubsub.egg-info/requires.txt
src/sentry_redispubsub.egg-info/top_level.txt