Metadata-Version: 1.1
Name: sentry-redispubsub
Version: 0.0.1
Summary: A Sentry extension which sends errors to a Redis pub/sub queue
Home-page: https://github.com/innogames/sentry-redispubsub
Author: Anthony Boah
Author-email: anthony.boah@innogames.com
License: WTFPL
Keywords: sentry redis pubsub message queue msg
Platform: UNKNOWN
Classifier: Intended Audience :: Developers
Classifier: Intended Audience :: System Administrators
Classifier: Operating System :: OS Independent
Classifier: Programming Language :: Python
Classifier: Framework :: Django
Classifier: Topic :: Software Development
